{
    "wallpaper": "/home/lamb/Wallpapers/AnimeBackgrounds-master/1mIA3Jf.png",
    "alpha": "100",
    "special": {
        "background": "#483836",
        "foreground": "#f4eae3",
        "cursor": "#f4eae3"
    },
    "colors": {
        "color0": "#483836",
        "color1": "#EC9AA5",
        "color2": "#C5A7A5",
        "color3": "#EFACB3",
        "color4": "#C9BDC1",
        "color5": "#F2BCC3",
        "color6": "#F5CED0",
        "color7": "#f4eae3",
        "color8": "#aaa39e",
        "color9": "#EC9AA5",
        "color10": "#C5A7A5",
        "color11": "#EFACB3",
        "color12": "#C9BDC1",
        "color13": "#F2BCC3",
        "color14": "#F5CED0",
        "color15": "#f4eae3"
    }
}